<?xml version="1.0" encoding="UTF-8"?>
<GenRun Id="impl_1" LaunchPart="xc7s25csga324-1" LaunchTime="1720652531">
  <File Type="POSTROUTE-PHYSOPT-RQS-RPT" Name="postroute_physopt_report_qor_suggestions_0.rpt"/>
  <File Type="ROUTE-RQS-RPT" Name="route_report_qor_suggestions_0.rpt"/>
  <File Type="POSTROUTE-PHYSOPT-RQS" Name="test_200_postroute_physopted.rqs"/>
  <File Type="ROUTE-RQS" Name="test_200_routed.rqs"/>
  <File Type="WBT-USG" Name="usage_statistics_webtalk.html"/>
  <File Type="RDI-RDI" Name="test_200.vdi"/>
  <File Type="BG-DRC" Name="test_200.drc"/>
  <File Type="BG-BGN" Name="test_200.bgn"/>
  <File Type="BITSTR-SYSDEF" Name="test_200.sysdef"/>
  <File Type="BITSTR-LTX" Name="debug_nets.ltx"/>
  <File Type="BITSTR-LTX" Name="test_200.ltx"/>
  <File Type="RBD_FILE" Name="test_200.rbd"/>
  <File Type="NPI_FILE" Name="test_200.npi"/>
  <File Type="RNPI_FILE" Name="test_200.rnpi"/>
  <File Type="CFI_FILE" Name="test_200.cfi"/>
  <File Type="RCFI_FILE" Name="test_200.rcfi"/>
  <File Type="PL-PDI-FILE" Name="test_200_pld.pdi"/>
  <File Type="BOOT-PDI-FILE" Name="test_200_boot.pdi"/>
  <File Type="PDI-FILE" Name="test_200.pdi"/>
  <File Type="BITSTR-MMI" Name="test_200.mmi"/>
  <File Type="BITSTR-BMM" Name="test_200_bd.bmm"/>
  <File Type="BITSTR-NKY" Name="test_200.nky"/>
  <File Type="BITSTR-RBT" Name="test_200.rbt"/>
  <File Type="BITSTR-MSK" Name="test_200.msk"/>
  <File Type="BG-BIN" Name="test_200.bin"/>
  <File Type="BG-BIT" Name="test_200.bit"/>
  <File Type="POSTROUTE-PHYSOPT-BUS-SKEW-RPX" Name="test_200_bus_skew_postroute_physopted.rpx"/>
  <File Type="POSTROUTE-PHYSOPT-BUS-SKEW-PB" Name="test_200_bus_skew_postroute_physopted.pb"/>
  <File Type="POSTROUTE-PHYSOPT-BUS-SKEW" Name="test_200_bus_skew_postroute_physopted.rpt"/>
  <File Type="POSTROUTE-PHYSOPT-TIMING-RPX" Name="test_200_timing_summary_postroute_physopted.rpx"/>
  <File Type="POSTROUTE-PHYSOPT-TIMING-PB" Name="test_200_timing_summary_postroute_physopted.pb"/>
  <File Type="POSTROUTE-PHYSOPT-TIMING" Name="test_200_timing_summary_postroute_physopted.rpt"/>
  <File Type="POSTROUTE-PHYSOPT-BLACKBOX-DCP" Name="test_200_postroute_physopt_bb.dcp"/>
  <File Type="POSTROUTE-PHYSOPT-DCP" Name="test_200_postroute_physopt.dcp"/>
  <File Type="ROUTE-RQS-PB" Name="test_200_rqs_routed.pb"/>
  <File Type="ROUTE-BUS-SKEW-RPX" Name="test_200_bus_skew_routed.rpx"/>
  <File Type="ROUTE-BUS-SKEW-PB" Name="test_200_bus_skew_routed.pb"/>
  <File Type="ROUTE-BUS-SKEW" Name="test_200_bus_skew_routed.rpt"/>
  <File Type="ROUTE-CLK" Name="test_200_clock_utilization_routed.rpt"/>
  <File Type="ROUTE-SIMILARITY" Name="test_200_incremental_reuse_routed.rpt"/>
  <File Type="ROUTE-TIMING-RPX" Name="test_200_timing_summary_routed.rpx"/>
  <File Type="ROUTE-TIMING-PB" Name="test_200_timing_summary_routed.pb"/>
  <File Type="ROUTE-TIMINGSUMMARY" Name="test_200_timing_summary_routed.rpt"/>
  <File Type="ROUTE-STATUS-PB" Name="test_200_route_status.pb"/>
  <File Type="ROUTE-STATUS" Name="test_200_route_status.rpt"/>
  <File Type="ROUTE-PWR-RPX" Name="test_200_power_routed.rpx"/>
  <File Type="ROUTE-PWR-SUM" Name="test_200_power_summary_routed.pb"/>
  <File Type="ROUTE-PWR" Name="test_200_power_routed.rpt"/>
  <File Type="ROUTE-METHODOLOGY-DRC-PB" Name="test_200_methodology_drc_routed.pb"/>
  <File Type="ROUTE-METHODOLOGY-DRC-RPX" Name="test_200_methodology_drc_routed.rpx"/>
  <File Type="ROUTE-METHODOLOGY-DRC" Name="test_200_methodology_drc_routed.rpt"/>
  <File Type="ROUTE-DRC-RPX" Name="test_200_drc_routed.rpx"/>
  <File Type="ROUTE-DRC-PB" Name="test_200_drc_routed.pb"/>
  <File Type="ROUTE-DRC" Name="test_200_drc_routed.rpt"/>
  <File Type="ROUTE-BLACKBOX-DCP" Name="test_200_routed_bb.dcp"/>
  <File Type="ROUTE-DCP" Name="test_200_routed.dcp"/>
  <File Type="ROUTE-ERROR-DCP" Name="test_200_routed_error.dcp"/>
  <File Type="PHYSOPT-TIMING" Name="test_200_timing_summary_physopted.rpt"/>
  <File Type="PHYSOPT-DRC" Name="test_200_drc_physopted.rpt"/>
  <File Type="PHYSOPT-DCP" Name="test_200_physopt.dcp"/>
  <File Type="POSTPLACE-PWROPT-TIMING" Name="test_200_timing_summary_postplace_pwropted.rpt"/>
  <File Type="POSTPLACE-PWROPT-DCP" Name="test_200_postplace_pwropt.dcp"/>
  <File Type="PLACE-RQA-PB" Name="test_200_rqa_placed.pb"/>
  <File Type="PLACE-TIMING" Name="test_200_timing_summary_placed.rpt"/>
  <File Type="PLACE-PRE-SIMILARITY" Name="test_200_incremental_reuse_pre_placed.rpt"/>
  <File Type="PLACE-SIMILARITY" Name="test_200_incremental_reuse_placed.rpt"/>
  <File Type="PLACE-CTRL" Name="test_200_control_sets_placed.rpt"/>
  <File Type="PLACE-UTIL-PB" Name="test_200_utilization_placed.pb"/>
  <File Type="PLACE-UTIL" Name="test_200_utilization_placed.rpt"/>
  <File Type="PLACE-CLK" Name="test_200_clock_utilization_placed.rpt"/>
  <File Type="PLACE-IO" Name="test_200_io_placed.rpt"/>
  <File Type="PLACE-DCP" Name="test_200_placed.dcp"/>
  <File Type="PWROPT-TIMING" Name="test_200_timing_summary_pwropted.rpt"/>
  <File Type="PWROPT-DRC" Name="test_200_drc_pwropted.rpt"/>
  <File Type="PWROPT-DCP" Name="test_200_pwropt.dcp"/>
  <File Type="OPT-RQA-PB" Name="test_200_rqa_opted.pb"/>
  <File Type="OPT-TIMING" Name="test_200_timing_summary_opted.rpt"/>
  <File Type="OPT-HWDEF" Name="test_200.hwdef"/>
  <File Type="OPT-METHODOLOGY-DRC" Name="test_200_methodology_drc_opted.rpt"/>
  <File Type="OPT-DRC" Name="test_200_drc_opted.rpt"/>
  <File Type="OPT-DCP" Name="test_200_opt.dcp"/>
  <File Type="INIT-TIMING" Name="test_200_timing_summary_init.rpt"/>
  <File Type="REPORTS-TCL" Name="test_200_reports.tcl"/>
  <File Type="PA-TCL" Name="test_200.tcl"/>
  <FileSet Name="sources" Type="DesignSrcs" RelSrcDir="$PSRCDIR/sources_1" RelGenDir="$PGENDIR/sources_1">
    <Filter Type="Srcs"/>
    <File Path="$PSRCDIR/sources_1/new/test_200.v">
      <FileInfo>
        <Attr Name="UsedIn" Val="synthesis"/>
        <Attr Name="UsedIn" Val="implementation"/>
        <Attr Name="UsedIn" Val="simulation"/>
      </FileInfo>
    </File>
    <File Path="$PSRCDIR/sources_1/bd/design_1/design_1.bd">
      <FileInfo>
        <Attr Name="AutoDisabled" Val="1"/>
        <Attr Name="UsedIn" Val="synthesis"/>
        <Attr Name="UsedIn" Val="implementation"/>
        <Attr Name="UsedIn" Val="simulation"/>
      </FileInfo>
    </File>
    <Config>
      <Option Name="DesignMode" Val="RTL"/>
      <Option Name="TopModule" Val="test_200"/>
      <Option Name="TopAutoSet" Val="TRUE"/>
    </Config>
  </FileSet>
  <FileSet Name="constrs_in" Type="Constrs" RelSrcDir="$PSRCDIR/constrs_1" RelGenDir="$PGENDIR/constrs_1">
    <Filter Type="Constrs"/>
    <File Path="$PSRCDIR/constrs_1/new/arty_s7-25.xdc">
      <FileInfo>
        <Attr Name="UsedIn" Val="synthesis"/>
        <Attr Name="UsedIn" Val="implementation"/>
      </FileInfo>
    </File>
    <Config>
      <Option Name="ConstrsType" Val="XDC"/>
    </Config>
  </FileSet>
  <FileSet Name="utils" Type="Utils" RelSrcDir="$PSRCDIR/utils_1" RelGenDir="$PGENDIR/utils_1">
    <Filter Type="Utils"/>
    <File Path="$PSRCDIR/utils_1/imports/synth_1/test_200.dcp">
      <FileInfo>
        <Attr Name="UsedIn" Val="synthesis"/>
        <Attr Name="UsedIn" Val="implementation"/>
        <Attr Name="UsedInSteps" Val="synth_1"/>
        <Attr Name="AutoDcp" Val="1"/>
      </FileInfo>
    </File>
    <Config>
      <Option Name="TopAutoSet" Val="TRUE"/>
    </Config>
  </FileSet>
  <Strategy Version="1" Minor="2">
    <StratHandle Name="Vivado Implementation Defaults" Flow="Vivado Implementation 2023"/>
    <Step Id="init_design"/>
    <Step Id="opt_design"/>
    <Step Id="power_opt_design"/>
    <Step Id="place_design"/>
    <Step Id="post_place_power_opt_design"/>
    <Step Id="phys_opt_design"/>
    <Step Id="route_design"/>
    <Step Id="post_route_phys_opt_design"/>
    <Step Id="write_bitstream"/>
  </Strategy>
  <BlockFileSet Type="BlockSrcs" Name="clk_wiz_0"/>
</GenRun>
